motulco/__init__.py
motulco/colors_utils.py
motulco/df_utils.py
motulco/doc_utils.py
motulco/excel_utils.py
motulco/pdf_utils.py
motulco/ppt_utils.py
motulco/py_utils.py
motulco/shapes_utils.py
motulco-0.2.0.dist-info/licenses/LICENSE
motulco-0.2.0.dist-info/METADATA
motulco-0.2.0.dist-info/WHEEL
motulco-0.2.0.dist-info/top_level.txt
motulco-0.2.0.dist-info/RECORD
