Metadata-Version: 2.4
Name: motulco
Version: 0.2.0
Summary: Librería de Python para manejo de archivos y DataFrames de Daniel Ochoa
Author-email: DanielOchoa <df.ochoa202@gmail.com>
Requires-Python: >=3.8
License-File: LICENSE
Requires-Dist: pandas>=2.0.0
Requires-Dist: numpy>=1.26.0
Requires-Dist: openpyxl>=3.1.0
Requires-Dist: unidecode>=1.3.6
Requires-Dist: pywin32>=306
Requires-Dist: pypdf>=4.0.0
Requires-Dist: Pillow>=10.0.0
Requires-Dist: nbformat>=5.9.0
Requires-Dist: nbconvert>=7.9.0
Requires-Dist: matplotlib>=3.8.0
Requires-Dist: html2image>=2.0.4
Dynamic: license-file
